<?xml version="1.0" encoding="UTF-8" standalone="yes"?>
<isd>
	<IMD>
		<VERSION>28.3</VERSION>
		<GENERATIONTIME>2024-01-11T21:08:16.000000Z</GENERATIONTIME>
		<PRODUCTORDERID>016182874010_01_P001</PRODUCTORDERID>
		<PRODUCTCATALOGID>A0100106EA5BF400</PRODUCTCATALOGID>
		<CHILDCATALOGID>20700106EA5BF500</CHILDCATALOGID>
		<IMAGEDESCRIPTOR>OrthoRectified3</IMAGEDESCRIPTOR>
		<PRODUCTSCALE>1:12,000</PRODUCTSCALE>
		<PRODUCTACCURACY>1.016000000000000e+01</PRODUCTACCURACY>
		<RMSE2D>6.180000000000000e+00</RMSE2D>
		<BANDID>Multi</BANDID>
		<PANSHARPENALGORITHM>None</PANSHARPENALGORITHM>
		<NUMROWS>7596</NUMROWS>
		<NUMCOLUMNS>7397</NUMCOLUMNS>
		<PRODUCTLEVEL>LV3D</PRODUCTLEVEL>
		<PRODUCTTYPE>Ortho</PRODUCTTYPE>
		<NUMBEROFLOOKS>1</NUMBEROFLOOKS>
		<RADIOMETRICLEVEL>Corrected</RADIOMETRICLEVEL>
		<RADIOMETRICENHANCEMENT>Off</RADIOMETRICENHANCEMENT>
		<BITSPERPIXEL>16</BITSPERPIXEL>
		<COMPRESSIONTYPE>None</COMPRESSIONTYPE>
		<OUTPUTFORMAT>GeoTIFF</OUTPUTFORMAT>
		<BAND_C>
			<ULLON>2.482122045000000e+01</ULLON>
			<ULLAT>6.427588667000001e+01</ULLAT>
			<ULHAE>9.311000000000000e+01</ULHAE>
			<URLON>2.512648772000000e+01</URLON>
			<URLAT>6.428011470000000e+01</URLAT>
			<URHAE>1.360000000000000e+02</URHAE>
			<LRLON>2.513567693000000e+01</LRLON>
			<LRLAT>6.414387583000000e+01</LRLAT>
			<LRHAE>1.174500000000000e+02</LRHAE>
			<LLLON>2.483190426000000e+01</LLLON>
			<LLLAT>6.413967328000000e+01</LLLAT>
			<LLHAE>1.167000000000000e+02</LLHAE>
			<ABSCALFACTOR>2.215385000000000e-02</ABSCALFACTOR>
			<EFFECTIVEBANDWIDTH>4.730000000000000e-02</EFFECTIVEBANDWIDTH>
			<TDILEVEL>10</TDILEVEL>
		</BAND_C>
		<BAND_B>
			<ULLON>2.482122045000000e+01</ULLON>
			<ULLAT>6.427588667000001e+01</ULLAT>
			<ULHAE>9.311000000000000e+01</ULHAE>
			<URLON>2.512648772000000e+01</URLON>
			<URLAT>6.428011470000000e+01</URLAT>
			<URHAE>1.360000000000000e+02</URHAE>
			<LRLON>2.513567693000000e+01</LRLON>
			<LRLAT>6.414387583000000e+01</LRLAT>
			<LRHAE>1.174500000000000e+02</LRHAE>
			<LLLON>2.483190426000000e+01</LLLON>
			<LLLAT>6.413967328000000e+01</LLLAT>
			<LLHAE>1.167000000000000e+02</LLHAE>
			<ABSCALFACTOR>3.006957000000000e-02</ABSCALFACTOR>
			<EFFECTIVEBANDWIDTH>5.430000000000000e-02</EFFECTIVEBANDWIDTH>
			<TDILEVEL>6</TDILEVEL>
		</BAND_B>
		<BAND_G>
			<ULLON>2.482122045000000e+01</ULLON>
			<ULLAT>6.427588667000001e+01</ULLAT>
			<ULHAE>9.311000000000000e+01</ULHAE>
			<URLON>2.512648772000000e+01</URLON>
			<URLAT>6.428011470000000e+01</URLAT>
			<URHAE>1.360000000000000e+02</URHAE>
			<LRLON>2.513567693000000e+01</LRLON>
			<LRLAT>6.414387583000000e+01</LRLAT>
			<LRHAE>1.174500000000000e+02</LRHAE>
			<LLLON>2.483190426000000e+01</LLLON>
			<LLLAT>6.413967328000000e+01</LLLAT>
			<LLHAE>1.167000000000000e+02</LLHAE>
			<ABSCALFACTOR>2.304348000000000e-02</ABSCALFACTOR>
			<EFFECTIVEBANDWIDTH>6.300000000000000e-02</EFFECTIVEBANDWIDTH>
			<TDILEVEL>6</TDILEVEL>
		</BAND_G>
		<BAND_Y>
			<ULLON>2.482122045000000e+01</ULLON>
			<ULLAT>6.427588667000001e+01</ULLAT>
			<ULHAE>9.311000000000000e+01</ULHAE>
			<URLON>2.512648772000000e+01</URLON>
			<URLAT>6.428011470000000e+01</URLAT>
			<URHAE>1.360000000000000e+02</URHAE>
			<LRLON>2.513567693000000e+01</LRLON>
			<LRLAT>6.414387583000000e+01</LRLAT>
			<LRHAE>1.174500000000000e+02</LRHAE>
			<LLLON>2.483190426000000e+01</LLLON>
			<LLLAT>6.413967328000000e+01</LLLAT>
			<LLHAE>1.167000000000000e+02</LLHAE>
			<ABSCALFACTOR>2.073043000000000e-02</ABSCALFACTOR>
			<EFFECTIVEBANDWIDTH>3.740000000000000e-02</EFFECTIVEBANDWIDTH>
			<TDILEVEL>6</TDILEVEL>
		</BAND_Y>
		<BAND_R>
			<ULLON>2.482122045000000e+01</ULLON>
			<ULLAT>6.427588667000001e+01</ULLAT>
			<ULHAE>9.311000000000000e+01</ULHAE>
			<URLON>2.512648772000000e+01</URLON>
			<URLAT>6.428011470000000e+01</URLAT>
			<URHAE>1.360000000000000e+02</URHAE>
			<LRLON>2.513567693000000e+01</LRLON>
			<LRLAT>6.414387583000000e+01</LRLAT>
			<LRHAE>1.174500000000000e+02</LRHAE>
			<LLLON>2.483190426000000e+01</LLLON>
			<LLLAT>6.413967328000000e+01</LLLAT>
			<LLHAE>1.167000000000000e+02</LLHAE>
			<ABSCALFACTOR>1.862609000000000e-02</ABSCALFACTOR>
			<EFFECTIVEBANDWIDTH>5.740000000000000e-02</EFFECTIVEBANDWIDTH>
			<TDILEVEL>6</TDILEVEL>
		</BAND_R>
		<BAND_RE>
			<ULLON>2.482122045000000e+01</ULLON>
			<ULLAT>6.427588667000001e+01</ULLAT>
			<ULHAE>9.311000000000000e+01</ULHAE>
			<URLON>2.512648772000000e+01</URLON>
			<URLAT>6.428011470000000e+01</URLAT>
			<URHAE>1.360000000000000e+02</URHAE>
			<LRLON>2.513567693000000e+01</LRLON>
			<LRLAT>6.414387583000000e+01</LRLAT>
			<LRHAE>1.174500000000000e+02</LRHAE>
			<LLLON>2.483190426000000e+01</LLLON>
			<LLLAT>6.413967328000000e+01</LLLAT>
			<LLHAE>1.167000000000000e+02</LLHAE>
			<ABSCALFACTOR>1.848696000000000e-02</ABSCALFACTOR>
			<EFFECTIVEBANDWIDTH>3.930000000000000e-02</EFFECTIVEBANDWIDTH>
			<TDILEVEL>6</TDILEVEL>
		</BAND_RE>
		<BAND_N>
			<ULLON>2.482122045000000e+01</ULLON>
			<ULLAT>6.427588667000001e+01</ULLAT>
			<ULHAE>9.311000000000000e+01</ULHAE>
			<URLON>2.512648772000000e+01</URLON>
			<URLAT>6.428011470000000e+01</URLAT>
			<URHAE>1.360000000000000e+02</URHAE>
			<LRLON>2.513567693000000e+01</LRLON>
			<LRLAT>6.414387583000000e+01</LRLAT>
			<LRHAE>1.174500000000000e+02</LRHAE>
			<LLLON>2.483190426000000e+01</LLLON>
			<LLLAT>6.413967328000000e+01</LLLAT>
			<LLHAE>1.167000000000000e+02</LLHAE>
			<ABSCALFACTOR>2.064348000000000e-02</ABSCALFACTOR>
			<EFFECTIVEBANDWIDTH>9.890000000000000e-02</EFFECTIVEBANDWIDTH>
			<TDILEVEL>6</TDILEVEL>
		</BAND_N>
		<BAND_N2>
			<ULLON>2.482122045000000e+01</ULLON>
			<ULLAT>6.427588667000001e+01</ULLAT>
			<ULHAE>9.311000000000000e+01</ULHAE>
			<URLON>2.512648772000000e+01</URLON>
			<URLAT>6.428011470000000e+01</URLAT>
			<URHAE>1.360000000000000e+02</URHAE>
			<LRLON>2.513567693000000e+01</LRLON>
			<LRLAT>6.414387583000000e+01</LRLAT>
			<LRHAE>1.174500000000000e+02</LRHAE>
			<LLLON>2.483190426000000e+01</LLLON>
			<LLLAT>6.413967328000000e+01</LLLAT>
			<LLHAE>1.167000000000000e+02</LLHAE>
			<ABSCALFACTOR>2.164103000000000e-02</ABSCALFACTOR>
			<EFFECTIVEBANDWIDTH>9.959999999999999e-02</EFFECTIVEBANDWIDTH>
			<TDILEVEL>10</TDILEVEL>
		</BAND_N2>
		<IMAGE>
			<SATID>WV02</SATID>
			<MODE>FullSwath</MODE>
			<SCANDIRECTION>Reverse</SCANDIRECTION>
			<CATID>10300100A7958300</CATID>
			<FIRSTLINETIME>2020-06-02T09:35:45.139073Z</FIRSTLINETIME>
			<AVGLINERATE>5.000010000000000e+03</AVGLINERATE>
			<EXPOSUREDURATION>2.000000000000000e-04</EXPOSUREDURATION>
			<MINCOLLECTEDROWGSD>2.080000000000000e+00</MINCOLLECTEDROWGSD>
			<MAXCOLLECTEDROWGSD>2.106000000000000e+00</MAXCOLLECTEDROWGSD>
			<MEANCOLLECTEDROWGSD>2.094000000000000e+00</MEANCOLLECTEDROWGSD>
			<MINCOLLECTEDCOLGSD>2.232000000000000e+00</MINCOLLECTEDCOLGSD>
			<MAXCOLLECTEDCOLGSD>2.253000000000000e+00</MAXCOLLECTEDCOLGSD>
			<MEANCOLLECTEDCOLGSD>2.243000000000000e+00</MEANCOLLECTEDCOLGSD>
			<MEANCOLLECTEDGSD>2.167000000000000e+00</MEANCOLLECTEDGSD>
			<ROWUNCERTAINTY>7.660000000000000e+00</ROWUNCERTAINTY>
			<COLUNCERTAINTY>1.334000000000000e+01</COLUNCERTAINTY>
			<MINSUNAZ>1.654000000000000e+02</MINSUNAZ>
			<MAXSUNAZ>1.654000000000000e+02</MAXSUNAZ>
			<MEANSUNAZ>1.654000000000000e+02</MEANSUNAZ>
			<MINSUNEL>4.760000000000000e+01</MINSUNEL>
			<MAXSUNEL>4.770000000000000e+01</MAXSUNEL>
			<MEANSUNEL>4.760000000000000e+01</MEANSUNEL>
			<MINSATAZ>6.210000000000000e+01</MINSATAZ>
			<MAXSATAZ>6.330000000000000e+01</MAXSATAZ>
			<MEANSATAZ>6.270000000000000e+01</MEANSATAZ>
			<MINSATEL>6.380000000000000e+01</MINSATEL>
			<MAXSATEL>6.430000000000000e+01</MAXSATEL>
			<MEANSATEL>6.400000000000000e+01</MEANSATEL>
			<MININTRACKVIEWANGLE>1.450000000000000e+01</MININTRACKVIEWANGLE>
			<MAXINTRACKVIEWANGLE>1.600000000000000e+01</MAXINTRACKVIEWANGLE>
			<MEANINTRACKVIEWANGLE>1.530000000000000e+01</MEANINTRACKVIEWANGLE>
			<MINCROSSTRACKVIEWANGLE>1.730000000000000e+01</MINCROSSTRACKVIEWANGLE>
			<MAXCROSSTRACKVIEWANGLE>1.760000000000000e+01</MAXCROSSTRACKVIEWANGLE>
			<MEANCROSSTRACKVIEWANGLE>1.740000000000000e+01</MEANCROSSTRACKVIEWANGLE>
			<MINOFFNADIRVIEWANGLE>2.260000000000000e+01</MINOFFNADIRVIEWANGLE>
			<MAXOFFNADIRVIEWANGLE>2.340000000000000e+01</MAXOFFNADIRVIEWANGLE>
			<MEANOFFNADIRVIEWANGLE>2.300000000000000e+01</MEANOFFNADIRVIEWANGLE>
			<PNIIRS>2.900000000000000e+00</PNIIRS>
			<CLOUDCOVER>0.000000000000000e+00</CLOUDCOVER>
			<RESAMPLINGKERNEL>CC</RESAMPLINGKERNEL>
			<POSITIONKNOWLEDGESRC>R</POSITIONKNOWLEDGESRC>
			<ATTITUDEKNOWLEDGESRC>R</ATTITUDEKNOWLEDGESRC>
			<REVNUMBER>55884</REVNUMBER>
		</IMAGE>
		<MAP_PROJECTED_PRODUCT>
			<EARLIESTACQTIME>2020-06-02T09:35:48.345491Z</EARLIESTACQTIME>
			<LATESTACQTIME>2020-06-02T09:35:48.345491Z</LATESTACQTIME>
			<DATUMNAME>WE</DATUMNAME>
			<SEMIMAJORAXIS>6.378137000000000e+06</SEMIMAJORAXIS>
			<INVERSEFLATTENING>2.982572235630000e+02</INVERSEFLATTENING>
			<DATUMOFFSETList>
				<DATUMOFFSET>0.000000000000000e+00 0.000000000000000e+00 0.000000000000000e+00</DATUMOFFSET>
			</DATUMOFFSETList>
			<MAPPROJNAME>UTM</MAPPROJNAME>
			<MAPPROJCODE>1</MAPPROJCODE>
			<MAPZONE>35</MAPZONE>
			<MAPHEMI>N</MAPHEMI>
			<MAPPROJPARAMList>
				<MAPPROJPARAM>0.000000000000000e+00 0.000000000000000e+00 0.000000000000000e+00 0.000000000000000e+00 0.000000000000000e+00 0.000000000000000e+00 0.000000000000000e+00 0.000000000000000e+00 0.000000000000000e+00 0.000000000000000e+00 0.000000000000000e+00 0.000000000000000e+00 0.000000000000000e+00 0.000000000000000e+00 0.000000000000000e+00</MAPPROJPARAM>
			</MAPPROJPARAMList>
			<PRODUCTUNITS>M</PRODUCTUNITS>
			<ORIGINX>3.944989999644300e+05</ORIGINX>
			<ORIGINY>7.129564999999690e+06</ORIGINY>
			<ORIENTATIONANGLE>0.000000000000000e+00</ORIENTATIONANGLE>
			<COLSPACING>2.000000000000000e+00</COLSPACING>
			<ROWSPACING>2.000000000000000e+00</ROWSPACING>
			<PRODUCTGSD>2.000000000000000e+00</PRODUCTGSD>
			<ULX>3.944989999644300e+05</ULX>
			<ULY>7.129564999999690e+06</ULY>
			<ULH>9.311000000000000e+01</ULH>
			<URX>4.092909999876400e+05</URX>
			<URY>7.129564999999670e+06</URY>
			<URH>1.360000000000000e+02</URH>
			<LRX>4.092909999880300e+05</LRX>
			<LRY>7.114374999999660e+06</LRY>
			<LRH>1.174500000000000e+02</LRH>
			<LLX>3.944989999655400e+05</LLX>
			<LLY>7.114374999999670e+06</LLY>
			<LLH>1.167000000000000e+02</LLH>
			<DEMCORRECTION>Fine DEM</DEMCORRECTION>
			<NUMGCP>0</NUMGCP>
		</MAP_PROJECTED_PRODUCT>
	</IMD>
	<TIL>
		<BANDID>Multi</BANDID>
		<NUMTILES>1</NUMTILES>
		<TILESIZEX>7397</TILESIZEX>
		<TILESIZEY>7596</TILESIZEY>
		<TILEUNITS>Pixels</TILEUNITS>
		<TILEOVERLAP>0</TILEOVERLAP>
		<TILE>
			<FILENAME>20JUN02093548-M3DS-016182874010_01_P001.TIF</FILENAME>
			<ULCOLOFFSET>0</ULCOLOFFSET>
			<ULROWOFFSET>0</ULROWOFFSET>
			<URCOLOFFSET>7396</URCOLOFFSET>
			<URROWOFFSET>0</URROWOFFSET>
			<LRCOLOFFSET>7396</LRCOLOFFSET>
			<LRROWOFFSET>7595</LRROWOFFSET>
			<LLCOLOFFSET>0</LLCOLOFFSET>
			<LLROWOFFSET>7595</LLROWOFFSET>
			<ULLON>2.482122045000000e+01</ULLON>
			<ULLAT>6.427588667000001e+01</ULLAT>
			<URLON>2.512648772000000e+01</URLON>
			<URLAT>6.428011470000000e+01</URLAT>
			<LRLON>2.513567693000000e+01</LRLON>
			<LRLAT>6.414387583000000e+01</LRLAT>
			<LLLON>2.483190426000000e+01</LLLON>
			<LLLAT>6.413967328000000e+01</LLLAT>
			<ULX>3.944989999644300e+05</ULX>
			<ULY>7.129564999999690e+06</ULY>
			<URX>4.092909999876400e+05</URX>
			<URY>7.129564999999670e+06</URY>
			<LRX>4.092909999880300e+05</LRX>
			<LRY>7.114374999999660e+06</LRY>
			<LLX>3.944989999655400e+05</LLX>
			<LLY>7.114374999999670e+06</LLY>
		</TILE>
	</TIL>
</isd>
